Metadata-Version: 1.0
Name: infinitythread
Version: 0.1.0
Summary: The infinity thread
Home-page: https://github.com/danielcoam/infinitythread
Author: RT
Author-email: danielcoam@gmail.com
License: MIT
Platform: UNKNOWN
